ivy_gym/__init__.py
ivy_gym/cartpole.py
ivy_gym/mountain_car.py
ivy_gym/pendulum.py
ivy_gym/reacher.py
ivy_gym/swimmer.py
ivy_gym-1.1.9.dist-info/LICENSE
ivy_gym-1.1.9.dist-info/METADATA
ivy_gym-1.1.9.dist-info/WHEEL
ivy_gym-1.1.9.dist-info/top_level.txt
ivy_gym-1.1.9.dist-info/RECORD
