Metadata-Version: 2.1
Name: ivy-gym
Version: 1.1.9
Summary: Fully differentiable reinforcement learning environments, written in Ivy.
Home-page: https://ivy-dl.org/gym
Author: Ivy Team
Author-email: ivydl.team@gmail.com
License: Apache 2.0
Project-URL: Docs, https://ivy-dl.org/gym/
Project-URL: Source, https://github.com/ivy-dl/gym
Platform: UNKNOWN
Classifier: License :: OSI Approved :: Apache Software License
License-File: LICENSE
Requires-Dist: gym
Requires-Dist: GLU
Requires-Dist: pyglet
